Metadata-Version: 2.1
Name: alpha-kentaurus-macos
Version: 0.1.10
Summary: Ah ah ah, you didn't say the magic word
Home-page: https://www.youtube.com/watch?v=RfiQYRn7fBg
Author: nope
Requires-Python: >=3.9.0
Classifier: Programming Language :: Python :: 3
Classifier: Programming Language :: Python :: 3.9
Classifier: Programming Language :: Python :: 3.10
Classifier: Programming Language :: Python :: 3.11
